blockcat/__init__.py
blockcat/__main__.py
blockcat/input.py
blockcat/json_query.py
blockcat/simple_query.py
blockcat-0.4.3.dist-info/METADATA
blockcat-0.4.3.dist-info/RECORD
blockcat-0.4.3.dist-info/WHEEL
blockcat-0.4.3.dist-info/entry_points.txt
blockcat-0.4.3.dist-info/top_level.txt
blockcat-0.4.3.dist-info/zip-safe
