Metadata-Version: 2.1
Name: blockcat
Version: 0.4.3
Summary: a tiny blockchain explorer supporting different blockchains
Home-page: https://github.com/mayotq/blockchain_explorer_clt
Author: mayotq
Author-email: mayotq@gmail.com
License: MIT
Keywords: python blockchain exploerer Bitcoin terminal
Platform: UNKNOWN
